cookiespy/__init__.py
cookiespy/cli.py
cookiespy/exporter.py
cookiespy/webapp.py
cookiespy-0.1.0.dist-info/METADATA
cookiespy-0.1.0.dist-info/WHEEL
cookiespy-0.1.0.dist-info/entry_points.txt
cookiespy-0.1.0.dist-info/top_level.txt
cookiespy-0.1.0.dist-info/RECORD
