Metadata-Version: 2.4
Name: cookiespy
Version: 0.1.0
Summary: A simple cookie inspection & export CLI tool.
Author-email: Fadhli Akbar <fadhliakbar125@gmail.com>
License: MIT
Project-URL: Homepage, https://github.com/fdhliakbar/cookiespy
Project-URL: Issues, https://github.com/fdhliakbar/cookiespy/issues
Keywords: cookies,cli,http,export
Classifier: Programming Language :: Python :: 3
Classifier: License :: OSI Approved :: MIT License
Classifier: Operating System :: OS Independent
Requires-Python: >=3.10
Requires-Dist: requests>=2.0
Requires-Dist: pytest>=6.0
